[
  {"id":1,"user_email":"emaiiil","user_desc":"Lorem Ipsum is simply dummy text of the printing and typesetting industry. Lorem Ipsum has been the industry's standard dummy text ever since the 1500s, when an unknown prin"},
  {"id":2,"user_email":"Millicent","user_desc":"Whatham"},
  {"id":3,"user_email":"Millicent","user_desc":"Whatham"},
  {"id":4,"user_email":"Millicent","user_desc":"Whatham"},
  {"id":4,"user_email":"Millicent","user_desc":"Whatham"},
  {"id":4,"user_email":"Millicent","user_desc":"Whatham"},
  {"id":4,"user_email":"Millicent","user_desc":"Whatham"},
  {"id":4,"user_email":"Millicent","user_desc":"Whatham"},
  {"id":4,"user_email":"Millicent","user_desc":"Whatham"},
  {"id":4,"user_email":"Millicent","user_desc":"Whatham"}
]